{
  "sessionId": "session_1760335046661",
  "pipelineId": "unknown",
  "startTime": 1760335046661,
  "status": "active",
  "operations": [
    {
      "operationId": "error_message_registered",
      "moduleId": "error-handler-registry",
      "position": "middle",
      "startTime": 1760335046661,
      "status": "running"
    },
    {
      "operationId": "error_message_registered",
      "moduleId": "error-handler-registry",
      "position": "middle",
      "startTime": 1760335046661,
      "status": "running"
    },
    {
      "operationId": "error_message_registered",
      "moduleId": "error-handler-registry",
      "position": "middle",
      "startTime": 1760335046661,
      "status": "running"
    },
    {
      "operationId": "error_message_registered",
      "moduleId": "error-handler-registry",
      "position": "middle",
      "startTime": 1760335046661,
      "status": "running"
    },
    {
      "operationId": "error_message_registered",
      "moduleId": "error-handler-registry",
      "position": "middle",
      "startTime": 1760335046661,
      "status": "running"
    },
    {
      "operationId": "error_handler_registered",
      "moduleId": "error-handler-registry",
      "position": "middle",
      "startTime": 1760335046661,
      "status": "running"
    }
  ]
}